add/__init__.py
add/add.py
samujipraneeth_add-0.1.0.dist-info/METADATA
samujipraneeth_add-0.1.0.dist-info/WHEEL
samujipraneeth_add-0.1.0.dist-info/top_level.txt
samujipraneeth_add-0.1.0.dist-info/RECORD
