Metadata-Version: 2.4
Name: samujipraneeth-add
Version: 0.1.0
Summary: which does addtion
Requires-Python: >=3.7
